setup.cfg
setup.py
scanman/__init__.py
scanman/main.py
scanman/scanman.kv
scanman/scanner.py
scanman.egg-info/PKG-INFO
scanman.egg-info/SOURCES.txt
scanman.egg-info/dependency_links.txt
scanman.egg-info/entry_points.txt
scanman.egg-info/requires.txt
scanman.egg-info/top_level.txt