Metadata-Version: 1.1
Name: scanman
Version: 0.8
Summary: A ScanSnap manager for Raspbery Pi
Home-page: https://github.com/rs/scanman
Author: Olivier Poitrey
Author-email: rs@rhapsodyk.net
License: UNKNOWN
Download-URL: https://github.com/rs/scanman/tarball/0.8
Keywords: scan,scansnap,sane,raspberry,kivy,paperless,office
Platform: UNKNOWN
Classifier: Development Status :: 3 - Alpha
Classifier: Environment :: Console :: Framebuffer
Classifier: Intended Audience :: End Users/Desktop
Classifier: License :: OSI Approved :: MIT License
Classifier: Operating System :: POSIX
Classifier: Programming Language :: Python :: 2.7
Classifier: Topic :: Office/Business
